gptalk/__init__.py
gptalk/gptalk.py
gptalk-0.0.4.5.dist-info/LICENSE.md
gptalk-0.0.4.5.dist-info/METADATA
gptalk-0.0.4.5.dist-info/WHEEL
gptalk-0.0.4.5.dist-info/top_level.txt
gptalk-0.0.4.5.dist-info/RECORD
