Metadata-Version: 2.1
Name: gptalk
Version: 0.0.4.5
Summary: Fast GPT-3 client for Windows and Unix that supports both text and speech in any language.
Author: 0ut0flin3
Author-email: 0ut0flin3 <0ut0flin3@protonmail.com>
License: Apache License
Project-URL: Homepage, https://github.com/0ut0flin3/gptalk
Keywords: speech-recognition,tts,gpt-3,chatgpt,speech-to-text,ai,dall-e
Classifier: License :: OSI Approved :: Apache Software License
Classifier: Programming Language :: Python
Classifier: Programming Language :: Python :: 3
Requires-Python: >=3
License-File: LICENSE.md
Requires-Dist: aiohttp (==3.8.3)
Requires-Dist: aiosignal (==1.3.1)
Requires-Dist: async-timeout (==4.0.2)
Requires-Dist: attrs (==22.2.0)
Requires-Dist: certifi (==2022.12.7)
Requires-Dist: charset-normalizer (==2.1.1)
Requires-Dist: click (==8.1.3)
Requires-Dist: frozenlist (==1.3.3)
Requires-Dist: gTTS (==2.3.1)
Requires-Dist: idna (==3.4)
Requires-Dist: multidict (==6.0.4)
Requires-Dist: openai (==0.26.1)
Requires-Dist: PyAudio (==0.2.13)
Requires-Dist: requests (==2.28.2)
Requires-Dist: SpeechRecognition (==3.9.0)
Requires-Dist: tqdm (==4.64.1)
Requires-Dist: urllib3 (==1.26.14)
Requires-Dist: yarl (==1.8.2)
Requires-Dist: dalle43 (==0.0.0.6)
